auralis_worker/README.md
auralis_worker/__init__.py
auralis_worker/cli.py
auralis_worker-0.2.8.dist-info/METADATA
auralis_worker-0.2.8.dist-info/WHEEL
auralis_worker-0.2.8.dist-info/entry_points.txt
auralis_worker-0.2.8.dist-info/top_level.txt
auralis_worker-0.2.8.dist-info/RECORD
