Metadata-Version: 2.4
Name: auralis-worker
Version: 0.2.8
Summary: Auralis Worker Node - Distributed AI Compute Platform
Author-email: Auralis Team <hello@auralis.dev>
License-Expression: MIT
Project-URL: Homepage, https://auralis.dev
Project-URL: Repository, https://github.com/auralis-dev/auralis
Project-URL: Documentation, https://docs.auralis.dev
Keywords: distributed,compute,ai,docker,worker
Classifier: Development Status :: 4 - Beta
Classifier: Environment :: Console
Classifier: Intended Audience :: Developers
Classifier: Operating System :: OS Independent
Classifier: Programming Language :: Python :: 3
Classifier: Programming Language :: Python :: 3.9
Classifier: Programming Language :: Python :: 3.10
Classifier: Programming Language :: Python :: 3.11
Classifier: Programming Language :: Python :: 3.12
Classifier: Programming Language :: Python :: 3.13
Classifier: Topic :: System :: Distributed Computing
Requires-Python: >=3.9
Requires-Dist: aiohttp>=3.9.0
Requires-Dist: certifi>=2024.0.0
